synaesthesia/__init__.py
synaesthesia/collates.py
synaesthesia/datamodule.py
synaesthesia/samplers.py
synaesthesia/utils.py
synaesthesia/abstract/__init__.py
synaesthesia/abstract/boundary_filtered_dataset.py
synaesthesia/abstract/concat_dataset.py
synaesthesia/abstract/conversion.py
synaesthesia/abstract/dataset_base.py
synaesthesia/abstract/filter_functions.py
synaesthesia/abstract/multi_signal_dataset.py
synaesthesia/abstract/sequential_dataset.py
synaesthesia/abstract/time_offset_dataset.py
synaesthesia/base_sensors/__init__.py
synaesthesia/base_sensors/csv_dataset.py
synaesthesia/base_sensors/image_dataset.py
synaesthesia/base_sensors/multi_file_dataset.py
synaesthesia/base_sensors/multi_spectral_imager_dataset.py
synaesthesia-0.1.0.dist-info/METADATA
synaesthesia-0.1.0.dist-info/WHEEL
synaesthesia-0.1.0.dist-info/licenses/LICENSE
synaesthesia-0.1.0.dist-info/RECORD
