Metadata-Version: 2.4
Name: synaesthesia
Version: 0.1.0
Summary: General data pipeline for pytorch lightning
License-File: LICENSE
Requires-Python: >=3.12
Requires-Dist: hydra-core>=1.3.2
Requires-Dist: kornia>=0.7.4
Requires-Dist: loguru>=0.7.3
Requires-Dist: opencv-python-headless>=4.10.0.84
Requires-Dist: pandas>=2.2.3
Requires-Dist: pillow>=11.0.0
Requires-Dist: pre-commit>=4.0.1
Requires-Dist: pyinputplus>=0.2.12
Requires-Dist: pytorch-lightning>=2.4.0
